timeof.py
timeof-0.0.1.dist-info/LICENSE
timeof-0.0.1.dist-info/METADATA
timeof-0.0.1.dist-info/WHEEL
timeof-0.0.1.dist-info/top_level.txt
timeof-0.0.1.dist-info/RECORD
