Metadata-Version: 2.1
Name: timeof
Version: 0.0.1
Summary: Eazy measure time of function execution
Home-page: UNKNOWN
Author: Ivan Krikunov
License: UNKNOWN
Platform: UNKNOWN
Classifier: Programming Language :: Python :: 3
Classifier: License :: OSI Approved :: MIT License
Classifier: Operating System :: OS Independent
Requires-Python: >=3.6
License-File: LICENSE
